{"functions_arraytool_index.md":"72966090","functions_browsertool_index.md":"a0023c46","functions_common_params_error.md":"82b1c4fe","functions_index.md":"51a48cf7","functions_numbertool_index.md":"d8b93db1","functions_objecttool_index.md":"18fb9b42","functions_storagetool_allkey.md":"514d56d0","functions_storagetool_clearfun.md":"17b0ad8b","functions_storagetool_delfun.md":"fdc8bd79","functions_storagetool_existfun.md":"38166fc9","functions_storagetool_getfun.md":"a6bbdf81","functions_storagetool_index.md":"7fc8498c","functions_storagetool_newstorage.md":"09ff5cb8","functions_storagetool_setfun.md":"b9e1d3ba","functions_stringtool_index.md":"37b7d860","functions_typetool_getarrayalltype.md":"f75618c5","functions_typetool_getarraytypedetail.md":"c34e9620","functions_typetool_getobjectalltype.md":"3821627e","functions_typetool_getobjecttypedetail.md":"7979662a","functions_typetool_gettype.md":"8bd81ba5","functions_typetool_index.md":"fab69a87","functions_typetool_isarray.md":"52388f96","functions_typetool_isbigint.md":"e3b0f390","functions_typetool_isboolean.md":"ab697087","functions_typetool_isdate.md":"3bc4eacf","functions_typetool_isfinite.md":"7a38ad22","functions_typetool_isfloat.md":"17467521","functions_typetool_isfunction.md":"88b9d2db","functions_typetool_isinfinite.md":"a68f7ff3","functions_typetool_isint.md":"ed8f8175","functions_typetool_isnan.md":"6bb408d7","functions_typetool_isnull.md":"9591e01f","functions_typetool_isnumber.md":"5181ae7f","functions_typetool_isobject.md":"27d19903","functions_typetool_isstring.md":"37ce924e","functions_typetool_issymbol.md":"83fca06f","functions_typetool_isundefined.md":"7a743e39","functions_urltool_converparamstourl.md":"1ad86f91","functions_urltool_geturlparams.md":"9f4d2074","functions_urltool_index.md":"f3bbdce3","guide_getting-started.md":"00f4b0a0","guide_index.md":"0bdf54ff","index.md":"b407bb88"}
